README.md
setup.py
v.txt
csip/__init__.py
csip/model_data_service.py
csip/utils.py
csip.egg-info/PKG-INFO
csip.egg-info/SOURCES.txt
csip.egg-info/dependency_links.txt
csip.egg-info/not-zip-safe
csip.egg-info/requires.txt
csip.egg-info/top_level.txt