Metadata-Version: 1.0
Name: csip
Version: 1.1.13
Summary: CSIP client library
Home-page: http://alm.engr.colostate.edu/cb/project/csip
Author: Olaf David
Author-email: odavid@colostate.edu
License: MIT
Platform: UNKNOWN
